pyramid_autodoc/__init__.py
pyramid_autodoc/utils.py
pyramid_autodoc-0.0.7.dist-info/DESCRIPTION.rst
pyramid_autodoc-0.0.7.dist-info/METADATA
pyramid_autodoc-0.0.7.dist-info/metadata.json
pyramid_autodoc-0.0.7.dist-info/pbr.json
pyramid_autodoc-0.0.7.dist-info/RECORD
pyramid_autodoc-0.0.7.dist-info/top_level.txt
pyramid_autodoc-0.0.7.dist-info/WHEEL
