Metadata-Version: 2.0
Name: pyramid-autodoc
Version: 0.0.7
Summary: Sphinx extension for documenting your Pyramid APIs.
Home-page: https://github.com/SurveyMonkey/pyramid_autodoc
Author: John Anderson
Author-email: johna@gmail.com
License: UNKNOWN
Platform: UNKNOWN
Requires-Dist: pyramid
Requires-Dist: sphinx
Requires-Dist: sphinxcontrib-httpdomain
